{
  "exec": {
    "backend": "native-stdio",
    "stdout": "",
    "stderr": "",
    "exit_code": null,
    "duration_ms": 706
  },
  "mcp_transcript": {
    "events": [
      {
        "direction": "client-to-server",
        "method": "initialize",
        "payload": {
          "id": 1,
          "jsonrpc": "2.0",
          "method": "initialize",
          "params": {
            "capabilities": {},
            "clientInfo": {
              "name": "mcp-sandboxscan",
              "version": "0.1.0"
            },
            "protocolVersion": "2025-06-18"
          }
        }
      },
      {
        "direction": "server-to-client",
        "method": null,
        "payload": {
          "id": 1,
          "jsonrpc": "2.0",
          "result": {
            "capabilities": {
              "tools": {
                "listChanged": true
              }
            },
            "protocolVersion": "2025-06-18",
            "serverInfo": {
              "name": "mobile-mcp",
              "version": "0.0.1"
            }
          }
        }
      },
      {
        "direction": "client-to-server",
        "method": "notifications/initialized",
        "payload": {
          "jsonrpc": "2.0",
          "method": "notifications/initialized"
        }
      },
      {
        "direction": "client-to-server",
        "method": "tools/list",
        "payload": {
          "id": 2,
          "jsonrpc": "2.0",
          "method": "tools/list",
          "params": {}
        }
      },
      {
        "direction": "server-to-client",
        "method": null,
        "payload": {
          "id": 2,
          "jsonrpc": "2.0",
          "result": {
            "tools": [
              {
                "annotations": {
                  "readOnlyHint": true
                },
                "description": "List all available devices. This includes both physical mobile devices and mobile simulators and emulators. It returns both Android and iOS devices.",
                "execution": {
                  "taskSupport": "forbidden"
                },
                "inputSchema": {
                  "$schema": "http://json-schema.org/draft-07/schema#",
                  "properties": {},
                  "type": "object"
                },
                "name": "mobile_list_available_devices",
                "title": "List Devices"
              },
              {
                "annotations": {
                  "readOnlyHint": true
                },
                "description": "List all the installed apps on the device",
                "execution": {
                  "taskSupport": "forbidden"
                },
                "inputSchema": {
                  "$schema": "http://json-schema.org/draft-07/schema#",
                  "properties": {
                    "device": {
                      "description": "The device identifier to use. Use mobile_list_available_devices to find which devices are available to you.",
                      "type": "string"
                    }
                  },
                  "required": [
                    "device"
                  ],
                  "type": "object"
                },
                "name": "mobile_list_apps",
                "title": "List Apps"
              },
              {
                "annotations": {
                  "destructiveHint": true
                },
                "description": "Launch an app on mobile device. Use this to open a specific app. You can find the package name of the app by calling list_apps_on_device.",
                "execution": {
                  "taskSupport": "forbidden"
                },
                "inputSchema": {
                  "$schema": "http://json-schema.org/draft-07/schema#",
                  "properties": {
                    "device": {
                      "description": "The device identifier to use. Use mobile_list_available_devices to find which devices are available to you.",
                      "type": "string"
                    },
                    "locale": {
                      "description": "Comma-separated BCP 47 locale tags to launch the app with (e.g., fr-FR,en-GB)",
                      "type": "string"
                    },
                    "packageName": {
                      "description": "The package name of the app to launch",
                      "type": "string"
                    }
                  },
                  "required": [
                    "device",
                    "packageName"
                  ],
                  "type": "object"
                },
                "name": "mobile_launch_app",
                "title": "Launch App"
              },
              {
                "annotations": {
                  "destructiveHint": true
                },
                "description": "Stop and terminate an app on mobile device",
                "execution": {
                  "taskSupport": "forbidden"
                },
                "inputSchema": {
                  "$schema": "http://json-schema.org/draft-07/schema#",
                  "properties": {
                    "device": {
                      "description": "The device identifier to use. Use mobile_list_available_devices to find which devices are available to you.",
                      "type": "string"
                    },
                    "packageName": {
                      "description": "The package name of the app to terminate",
                      "type": "string"
                    }
                  },
                  "required": [
                    "device",
                    "packageName"
                  ],
                  "type": "object"
                },
                "name": "mobile_terminate_app",
                "title": "Terminate App"
              },
              {
                "annotations": {
                  "destructiveHint": true
                },
                "description": "Install an app on mobile device",
                "execution": {
                  "taskSupport": "forbidden"
                },
                "inputSchema": {
                  "$schema": "http://json-schema.org/draft-07/schema#",
                  "properties": {
                    "device": {
                      "description": "The device identifier to use. Use mobile_list_available_devices to find which devices are available to you.",
                      "type": "string"
                    },
                    "path": {
                      "description": "The path to the app file to install. For iOS simulators, provide a .zip file or a .app directory. For Android provide an .apk file. For iOS real devices provide an .ipa file",
                      "type": "string"
                    }
                  },
                  "required": [
                    "device",
                    "path"
                  ],
                  "type": "object"
                },
                "name": "mobile_install_app",
                "title": "Install App"
              },
              {
                "annotations": {
                  "destructiveHint": true
                },
                "description": "Uninstall an app from mobile device",
                "execution": {
                  "taskSupport": "forbidden"
                },
                "inputSchema": {
                  "$schema": "http://json-schema.org/draft-07/schema#",
                  "properties": {
                    "bundle_id": {
                      "description": "Bundle identifier (iOS) or package name (Android) of the app to be uninstalled",
                      "type": "string"
                    },
                    "device": {
                      "description": "The device identifier to use. Use mobile_list_available_devices to find which devices are available to you.",
                      "type": "string"
                    }
                  },
                  "required": [
                    "device",
                    "bundle_id"
                  ],
                  "type": "object"
                },
                "name": "mobile_uninstall_app",
                "title": "Uninstall App"
              },
              {
                "annotations": {
                  "readOnlyHint": true
                },
                "description": "Get the screen size of the mobile device in pixels",
                "execution": {
                  "taskSupport": "forbidden"
                },
                "inputSchema": {
                  "$schema": "http://json-schema.org/draft-07/schema#",
                  "properties": {
                    "device": {
                      "description": "The device identifier to use. Use mobile_list_available_devices to find which devices are available to you.",
                      "type": "string"
                    }
                  },
                  "required": [
                    "device"
                  ],
                  "type": "object"
                },
                "name": "mobile_get_screen_size",
                "title": "Get Screen Size"
              },
              {
                "annotations": {
                  "destructiveHint": true
                },
                "description": "Click on the screen at given x,y coordinates. If clicking on an element, use the list_elements_on_screen tool to find the coordinates.",
                "execution": {
                  "taskSupport": "forbidden"
                },
                "inputSchema": {
                  "$schema": "http://json-schema.org/draft-07/schema#",
                  "properties": {
                    "device": {
                      "description": "The device identifier to use. Use mobile_list_available_devices to find which devices are available to you.",
                      "type": "string"
                    },
                    "x": {
                      "description": "The x coordinate to click on the screen, in pixels",
                      "type": "number"
                    },
                    "y": {
                      "description": "The y coordinate to click on the screen, in pixels",
                      "type": "number"
                    }
                  },
                  "required": [
                    "device",
                    "x",
                    "y"
                  ],
                  "type": "object"
                },
                "name": "mobile_click_on_screen_at_coordinates",
                "title": "Click Screen"
              },
              {
                "annotations": {
                  "destructiveHint": true
                },
                "description": "Double-tap on the screen at given x,y coordinates.",
                "execution": {
                  "taskSupport": "forbidden"
                },
                "inputSchema": {
                  "$schema": "http://json-schema.org/draft-07/schema#",
                  "properties": {
                    "device": {
                      "description": "The device identifier to use. Use mobile_list_available_devices to find which devices are available to you.",
                      "type": "string"
                    },
                    "x": {
                      "description": "The x coordinate to double-tap, in pixels",
                      "type": "number"
                    },
                    "y": {
                      "description": "The y coordinate to double-tap, in pixels",
                      "type": "number"
                    }
                  },
                  "required": [
                    "device",
                    "x",
                    "y"
                  ],
                  "type": "object"
                },
                "name": "mobile_double_tap_on_screen",
                "title": "Double Tap Screen"
              },
              {
                "annotations": {
                  "destructiveHint": true
                },
                "description": "Long press on the screen at given x,y coordinates. If long pressing on an element, use the list_elements_on_screen tool to find the coordinates.",
                "execution": {
                  "taskSupport": "forbidden"
                },
                "inputSchema": {
                  "$schema": "http://json-schema.org/draft-07/schema#",
                  "properties": {
                    "device": {
                      "description": "The device identifier to use. Use mobile_list_available_devices to find which devices are available to you.",
                      "type": "string"
                    },
                    "duration": {
                      "description": "Duration of the long press in milliseconds. Defaults to 500ms.",
                      "maximum": 10000,
                      "minimum": 1,
                      "type": "number"
                    },
                    "x": {
                      "description": "The x coordinate to long press on the screen, in pixels",
                      "type": "number"
                    },
                    "y": {
                      "description": "The y coordinate to long press on the screen, in pixels",
                      "type": "number"
                    }
                  },
                  "required": [
                    "device",
                    "x",
                    "y"
                  ],
                  "type": "object"
                },
                "name": "mobile_long_press_on_screen_at_coordinates",
                "title": "Long Press Screen"
              },
              {
                "annotations": {
                  "readOnlyHint": true
                },
                "description": "List elements on screen and their coordinates, with display text or accessibility label. Do not cache this result.",
                "execution": {
                  "taskSupport": "forbidden"
                },
                "inputSchema": {
                  "$schema": "http://json-schema.org/draft-07/schema#",
                  "properties": {
                    "device": {
                      "description": "The device identifier to use. Use mobile_list_available_devices to find which devices are available to you.",
                      "type": "string"
                    }
                  },
                  "required": [
                    "device"
                  ],
                  "type": "object"
                },
                "name": "mobile_list_elements_on_screen",
                "title": "List Screen Elements"
              },
              {
                "annotations": {
                  "destructiveHint": true
                },
                "description": "Press a button on device",
                "execution": {
                  "taskSupport": "forbidden"
                },
                "inputSchema": {
                  "$schema": "http://json-schema.org/draft-07/schema#",
                  "properties": {
                    "button": {
                      "description": "The button to press. Supported buttons: BACK (android only), HOME, VOLUME_UP, VOLUME_DOWN, ENTER, DPAD_CENTER (android tv only), DPAD_UP (android tv only), DPAD_DOWN (android tv only), DPAD_LEFT (android tv only), DPAD_RIGHT (android tv only)",
                      "type": "string"
                    },
                    "device": {
                      "description": "The device identifier to use. Use mobile_list_available_devices to find which devices are available to you.",
                      "type": "string"
                    }
                  },
                  "required": [
                    "device",
                    "button"
                  ],
                  "type": "object"
                },
                "name": "mobile_press_button",
                "title": "Press Button"
              },
              {
                "annotations": {
                  "destructiveHint": true
                },
                "description": "Open a URL in browser on device",
                "execution": {
                  "taskSupport": "forbidden"
                },
                "inputSchema": {
                  "$schema": "http://json-schema.org/draft-07/schema#",
                  "properties": {
                    "device": {
                      "description": "The device identifier to use. Use mobile_list_available_devices to find which devices are available to you.",
                      "type": "string"
                    },
                    "url": {
                      "description": "The URL to open",
                      "type": "string"
                    }
                  },
                  "required": [
                    "device",
                    "url"
                  ],
                  "type": "object"
                },
                "name": "mobile_open_url",
                "title": "Open URL"
              },
              {
                "annotations": {
                  "destructiveHint": true
                },
                "description": "Swipe on the screen",
                "execution": {
                  "taskSupport": "forbidden"
                },
                "inputSchema": {
                  "$schema": "http://json-schema.org/draft-07/schema#",
                  "properties": {
                    "device": {
                      "description": "The device identifier to use. Use mobile_list_available_devices to find which devices are available to you.",
                      "type": "string"
                    },
                    "direction": {
                      "description": "The direction to swipe",
                      "enum": [
                        "up",
                        "down",
                        "left",
                        "right"
                      ],
                      "type": "string"
                    },
                    "distance": {
                      "description": "The distance to swipe in pixels. Defaults to 400 pixels for iOS or 30% of screen dimension for Android",
                      "type": "number"
                    },
                    "x": {
                      "description": "The x coordinate to start the swipe from, in pixels. If not provided, uses center of screen",
                      "type": "number"
                    },
                    "y": {
                      "description": "The y coordinate to start the swipe from, in pixels. If not provided, uses center of screen",
                      "type": "number"
                    }
                  },
                  "required": [
                    "device",
                    "direction"
                  ],
                  "type": "object"
                },
                "name": "mobile_swipe_on_screen",
                "title": "Swipe Screen"
              },
              {
                "annotations": {
                  "destructiveHint": true
                },
                "description": "Type text into the focused element",
                "execution": {
                  "taskSupport": "forbidden"
                },
                "inputSchema": {
                  "$schema": "http://json-schema.org/draft-07/schema#",
                  "properties": {
                    "device": {
                      "description": "The device identifier to use. Use mobile_list_available_devices to find which devices are available to you.",
                      "type": "string"
                    },
                    "submit": {
                      "description": "Whether to submit the text. If true, the text will be submitted as if the user pressed the enter key.",
                      "type": "boolean"
                    },
                    "text": {
                      "description": "The text to type",
                      "type": "string"
                    }
                  },
                  "required": [
                    "device",
                    "text",
                    "submit"
                  ],
                  "type": "object"
                },
                "name": "mobile_type_keys",
                "title": "Type Text"
              },
              {
                "annotations": {
                  "destructiveHint": true
                },
                "description": "Save a screenshot of the mobile device to a file",
                "execution": {
                  "taskSupport": "forbidden"
                },
                "inputSchema": {
                  "$schema": "http://json-schema.org/draft-07/schema#",
                  "properties": {
                    "device": {
                      "description": "The device identifier to use. Use mobile_list_available_devices to find which devices are available to you.",
                      "type": "string"
                    },
                    "saveTo": {
                      "description": "The path to save the screenshot to. Filename must end with .png, .jpg, or .jpeg",
                      "type": "string"
                    }
                  },
                  "required": [
                    "device",
                    "saveTo"
                  ],
                  "type": "object"
                },
                "name": "mobile_save_screenshot",
                "title": "Save Screenshot"
              },
              {
                "annotations": {
                  "readOnlyHint": true
                },
                "description": "Take a screenshot of the mobile device. Use this to understand what's on screen, if you need to press an element that is available through view hierarchy then you must list elements on screen instead. Do not cache this result.",
                "execution": {
                  "taskSupport": "forbidden"
                },
                "inputSchema": {
                  "$schema": "http://json-schema.org/draft-07/schema#",
                  "properties": {
                    "device": {
                      "description": "The device identifier to use. Use mobile_list_available_devices to find which devices are available to you.",
                      "type": "string"
                    }
                  },
                  "required": [
                    "device"
                  ],
                  "type": "object"
                },
                "name": "mobile_take_screenshot",
                "title": "Take Screenshot"
              },
              {
                "annotations": {
                  "destructiveHint": true
                },
                "description": "Change the screen orientation of the device",
                "execution": {
                  "taskSupport": "forbidden"
                },
                "inputSchema": {
                  "$schema": "http://json-schema.org/draft-07/schema#",
                  "properties": {
                    "device": {
                      "description": "The device identifier to use. Use mobile_list_available_devices to find which devices are available to you.",
                      "type": "string"
                    },
                    "orientation": {
                      "description": "The desired orientation",
                      "enum": [
                        "portrait",
                        "landscape"
                      ],
                      "type": "string"
                    }
                  },
                  "required": [
                    "device",
                    "orientation"
                  ],
                  "type": "object"
                },
                "name": "mobile_set_orientation",
                "title": "Set Orientation"
              },
              {
                "annotations": {
                  "readOnlyHint": true
                },
                "description": "Get the current screen orientation of the device",
                "execution": {
                  "taskSupport": "forbidden"
                },
                "inputSchema": {
                  "$schema": "http://json-schema.org/draft-07/schema#",
                  "properties": {
                    "device": {
                      "description": "The device identifier to use. Use mobile_list_available_devices to find which devices are available to you.",
                      "type": "string"
                    }
                  },
                  "required": [
                    "device"
                  ],
                  "type": "object"
                },
                "name": "mobile_get_orientation",
                "title": "Get Orientation"
              },
              {
                "annotations": {
                  "destructiveHint": true
                },
                "description": "Start recording the screen of a mobile device. The recording runs in the background until stopped with mobile_stop_screen_recording. Returns the path where the recording will be saved.",
                "execution": {
                  "taskSupport": "forbidden"
                },
                "inputSchema": {
                  "$schema": "http://json-schema.org/draft-07/schema#",
                  "properties": {
                    "device": {
                      "description": "The device identifier to use. Use mobile_list_available_devices to find which devices are available to you.",
                      "type": "string"
                    },
                    "output": {
                      "description": "The file path to save the recording to. Filename must end with .mp4. If not provided, a temporary path will be used.",
                      "type": "string"
                    },
                    "timeLimit": {
                      "description": "Maximum recording duration in seconds. The recording will stop automatically after this time.",
                      "type": "number"
                    }
                  },
                  "required": [
                    "device"
                  ],
                  "type": "object"
                },
                "name": "mobile_start_screen_recording",
                "title": "Start Screen Recording"
              },
              {
                "annotations": {
                  "destructiveHint": true
                },
                "description": "Stop an active screen recording on a mobile device. Returns the file path, size, and approximate duration of the recording.",
                "execution": {
                  "taskSupport": "forbidden"
                },
                "inputSchema": {
                  "$schema": "http://json-schema.org/draft-07/schema#",
                  "properties": {
                    "device": {
                      "description": "The device identifier to use. Use mobile_list_available_devices to find which devices are available to you.",
                      "type": "string"
                    }
                  },
                  "required": [
                    "device"
                  ],
                  "type": "object"
                },
                "name": "mobile_stop_screen_recording",
                "title": "Stop Screen Recording"
              },
              {
                "annotations": {
                  "readOnlyHint": true
                },
                "description": "List crash reports available on the device",
                "execution": {
                  "taskSupport": "forbidden"
                },
                "inputSchema": {
                  "$schema": "http://json-schema.org/draft-07/schema#",
                  "properties": {
                    "device": {
                      "description": "The device identifier to use. Use mobile_list_available_devices to find which devices are available to you.",
                      "type": "string"
                    }
                  },
                  "required": [
                    "device"
                  ],
                  "type": "object"
                },
                "name": "mobile_list_crashes",
                "title": "List Crash Reports"
              },
              {
                "annotations": {
                  "readOnlyHint": true
                },
                "description": "Get the full content of a crash report by its ID. Use mobile_list_crashes to find available crash IDs.",
                "execution": {
                  "taskSupport": "forbidden"
                },
                "inputSchema": {
                  "$schema": "http://json-schema.org/draft-07/schema#",
                  "properties": {
                    "device": {
                      "description": "The device identifier to use. Use mobile_list_available_devices to find which devices are available to you.",
                      "type": "string"
                    },
                    "id": {
                      "description": "The crash report ID to retrieve",
                      "type": "string"
                    }
                  },
                  "required": [
                    "device",
                    "id"
                  ],
                  "type": "object"
                },
                "name": "mobile_get_crash",
                "title": "Get Crash Report"
              }
            ]
          }
        }
      },
      {
        "direction": "client-to-server",
        "method": "tools/call",
        "payload": {
          "id": 3,
          "jsonrpc": "2.0",
          "method": "tools/call",
          "params": {
            "arguments": {
              "device": "MCP_INPUT_CANARY_mobile_next__mobile_mcp",
              "id": "MCP_INPUT_CANARY_mobile_next__mobile_mcp"
            },
            "name": "mobile_get_crash"
          }
        }
      },
      {
        "direction": "server-to-client",
        "method": null,
        "payload": {
          "id": 3,
          "jsonrpc": "2.0",
          "result": {
            "content": [
              {
                "text": "Error: Command failed: /Users/zhuoran/Projects/MCP-SandboxScan/mcp-sandboxscan/corpus/clones/mobile-next__mobile-mcp/node_modules/mobilecli/bin/mobilecli-darwin-arm64 device crashes get MCP_INPUT_CANARY_mobile_next__mobile_mcp --device MCP_INPUT_CANARY_mobile_next__mobile_mcp\nerror finding device: device not found: MCP_INPUT_CANARY_mobile_next__mobile_mcp\n",
                "type": "text"
              }
            ],
            "isError": true
          }
        }
      },
      {
        "direction": "client-to-server",
        "method": "tools/call",
        "payload": {
          "id": 4,
          "jsonrpc": "2.0",
          "method": "tools/call",
          "params": {
            "arguments": {
              "device": "MCP_INPUT_CANARY_mobile_next__mobile_mcp",
              "x": 1.0,
              "y": 1.0
            },
            "name": "mobile_click_on_screen_at_coordinates"
          }
        }
      },
      {
        "direction": "server-to-client",
        "method": null,
        "payload": {
          "id": 4,
          "jsonrpc": "2.0",
          "result": {
            "content": [
              {
                "text": "Device \"MCP_INPUT_CANARY_mobile_next__mobile_mcp\" not found. Use the mobile_list_available_devices tool to see available devices.. Please fix the issue and try again.",
                "type": "text"
              }
            ]
          }
        }
      },
      {
        "direction": "client-to-server",
        "method": "tools/call",
        "payload": {
          "id": 5,
          "jsonrpc": "2.0",
          "method": "tools/call",
          "params": {
            "arguments": {
              "device": "MCP_INPUT_CANARY_mobile_next__mobile_mcp"
            },
            "name": "mobile_get_orientation"
          }
        }
      },
      {
        "direction": "server-to-client",
        "method": null,
        "payload": {
          "id": 5,
          "jsonrpc": "2.0",
          "result": {
            "content": [
              {
                "text": "Device \"MCP_INPUT_CANARY_mobile_next__mobile_mcp\" not found. Use the mobile_list_available_devices tool to see available devices.. Please fix the issue and try again.",
                "type": "text"
              }
            ]
          }
        }
      },
      {
        "direction": "client-to-server",
        "method": "tools/call",
        "payload": {
          "id": 6,
          "jsonrpc": "2.0",
          "method": "tools/call",
          "params": {
            "arguments": {
              "device": "MCP_INPUT_CANARY_mobile_next__mobile_mcp"
            },
            "name": "mobile_get_screen_size"
          }
        }
      },
      {
        "direction": "server-to-client",
        "method": null,
        "payload": {
          "id": 6,
          "jsonrpc": "2.0",
          "result": {
            "content": [
              {
                "text": "Device \"MCP_INPUT_CANARY_mobile_next__mobile_mcp\" not found. Use the mobile_list_available_devices tool to see available devices.. Please fix the issue and try again.",
                "type": "text"
              }
            ]
          }
        }
      },
      {
        "direction": "client-to-server",
        "method": "tools/call",
        "payload": {
          "id": 7,
          "jsonrpc": "2.0",
          "method": "tools/call",
          "params": {
            "arguments": {},
            "name": "mobile_list_available_devices"
          }
        }
      },
      {
        "direction": "server-to-client",
        "method": null,
        "payload": {
          "id": 7,
          "jsonrpc": "2.0",
          "result": {
            "content": [
              {
                "text": "{\"devices\":[]}",
                "type": "text"
              }
            ]
          }
        }
      },
      {
        "direction": "client-to-server",
        "method": "tools/call",
        "payload": {
          "id": 8,
          "jsonrpc": "2.0",
          "method": "tools/call",
          "params": {
            "arguments": {
              "device": "MCP_INPUT_CANARY_mobile_next__mobile_mcp"
            },
            "name": "mobile_list_crashes"
          }
        }
      },
      {
        "direction": "server-to-client",
        "method": null,
        "payload": {
          "id": 8,
          "jsonrpc": "2.0",
          "result": {
            "content": [
              {
                "text": "Error: Command failed: /Users/zhuoran/Projects/MCP-SandboxScan/mcp-sandboxscan/corpus/clones/mobile-next__mobile-mcp/node_modules/mobilecli/bin/mobilecli-darwin-arm64 device crashes list --device MCP_INPUT_CANARY_mobile_next__mobile_mcp\nerror finding device: device not found: MCP_INPUT_CANARY_mobile_next__mobile_mcp\n",
                "type": "text"
              }
            ],
            "isError": true
          }
        }
      },
      {
        "direction": "client-to-server",
        "method": "tools/call",
        "payload": {
          "id": 9,
          "jsonrpc": "2.0",
          "method": "tools/call",
          "params": {
            "arguments": {
              "device": "MCP_INPUT_CANARY_mobile_next__mobile_mcp"
            },
            "name": "mobile_list_elements_on_screen"
          }
        }
      },
      {
        "direction": "server-to-client",
        "method": null,
        "payload": {
          "id": 9,
          "jsonrpc": "2.0",
          "result": {
            "content": [
              {
                "text": "Device \"MCP_INPUT_CANARY_mobile_next__mobile_mcp\" not found. Use the mobile_list_available_devices tool to see available devices.. Please fix the issue and try again.",
                "type": "text"
              }
            ]
          }
        }
      },
      {
        "direction": "client-to-server",
        "method": "tools/call",
        "payload": {
          "id": 10,
          "jsonrpc": "2.0",
          "method": "tools/call",
          "params": {
            "arguments": {
              "device": "MCP_INPUT_CANARY_mobile_next__mobile_mcp",
              "x": 1.0,
              "y": 1.0
            },
            "name": "mobile_long_press_on_screen_at_coordinates"
          }
        }
      },
      {
        "direction": "server-to-client",
        "method": null,
        "payload": {
          "id": 10,
          "jsonrpc": "2.0",
          "result": {
            "content": [
              {
                "text": "Device \"MCP_INPUT_CANARY_mobile_next__mobile_mcp\" not found. Use the mobile_list_available_devices tool to see available devices.. Please fix the issue and try again.",
                "type": "text"
              }
            ]
          }
        }
      }
    ]
  },
  "events": [
    {
      "kind": "mcp-initialize",
      "actor": "mcp-client",
      "target": "initialize",
      "evidence": {
        "id": 1,
        "jsonrpc": "2.0",
        "method": "initialize",
        "params": {
          "capabilities": {},
          "clientInfo": {
            "name": "mcp-sandboxscan",
            "version": "0.1.0"
          },
          "protocolVersion": "2025-06-18"
        }
      }
    },
    {
      "kind": "mcp-tools-list",
      "actor": "mcp-client",
      "target": "tools/list",
      "evidence": {
        "id": 2,
        "jsonrpc": "2.0",
        "method": "tools/list",
        "params": {}
      }
    },
    {
      "kind": "mcp-tool-call",
      "actor": "mcp-client",
      "target": "tools/call",
      "evidence": {
        "id": 3,
        "jsonrpc": "2.0",
        "method": "tools/call",
        "params": {
          "arguments": {
            "device": "MCP_INPUT_CANARY_mobile_next__mobile_mcp",
            "id": "MCP_INPUT_CANARY_mobile_next__mobile_mcp"
          },
          "name": "mobile_get_crash"
        }
      }
    },
    {
      "kind": "mcp-tool-result",
      "actor": "mcp-server",
      "target": "mobile_get_crash",
      "evidence": {
        "response": {
          "id": 3,
          "jsonrpc": "2.0",
          "result": {
            "content": [
              {
                "text": "Error: Command failed: /Users/zhuoran/Projects/MCP-SandboxScan/mcp-sandboxscan/corpus/clones/mobile-next__mobile-mcp/node_modules/mobilecli/bin/mobilecli-darwin-arm64 device crashes get MCP_INPUT_CANARY_mobile_next__mobile_mcp --device MCP_INPUT_CANARY_mobile_next__mobile_mcp\nerror finding device: device not found: MCP_INPUT_CANARY_mobile_next__mobile_mcp\n",
                "type": "text"
              }
            ],
            "isError": true
          }
        },
        "tool_name": "mobile_get_crash"
      }
    },
    {
      "kind": "mcp-tool-call",
      "actor": "mcp-client",
      "target": "tools/call",
      "evidence": {
        "id": 4,
        "jsonrpc": "2.0",
        "method": "tools/call",
        "params": {
          "arguments": {
            "device": "MCP_INPUT_CANARY_mobile_next__mobile_mcp",
            "x": 1.0,
            "y": 1.0
          },
          "name": "mobile_click_on_screen_at_coordinates"
        }
      }
    },
    {
      "kind": "mcp-tool-result",
      "actor": "mcp-server",
      "target": "mobile_click_on_screen_at_coordinates",
      "evidence": {
        "response": {
          "id": 4,
          "jsonrpc": "2.0",
          "result": {
            "content": [
              {
                "text": "Device \"MCP_INPUT_CANARY_mobile_next__mobile_mcp\" not found. Use the mobile_list_available_devices tool to see available devices.. Please fix the issue and try again.",
                "type": "text"
              }
            ]
          }
        },
        "tool_name": "mobile_click_on_screen_at_coordinates"
      }
    },
    {
      "kind": "mcp-tool-call",
      "actor": "mcp-client",
      "target": "tools/call",
      "evidence": {
        "id": 5,
        "jsonrpc": "2.0",
        "method": "tools/call",
        "params": {
          "arguments": {
            "device": "MCP_INPUT_CANARY_mobile_next__mobile_mcp"
          },
          "name": "mobile_get_orientation"
        }
      }
    },
    {
      "kind": "mcp-tool-result",
      "actor": "mcp-server",
      "target": "mobile_get_orientation",
      "evidence": {
        "response": {
          "id": 5,
          "jsonrpc": "2.0",
          "result": {
            "content": [
              {
                "text": "Device \"MCP_INPUT_CANARY_mobile_next__mobile_mcp\" not found. Use the mobile_list_available_devices tool to see available devices.. Please fix the issue and try again.",
                "type": "text"
              }
            ]
          }
        },
        "tool_name": "mobile_get_orientation"
      }
    },
    {
      "kind": "mcp-tool-call",
      "actor": "mcp-client",
      "target": "tools/call",
      "evidence": {
        "id": 6,
        "jsonrpc": "2.0",
        "method": "tools/call",
        "params": {
          "arguments": {
            "device": "MCP_INPUT_CANARY_mobile_next__mobile_mcp"
          },
          "name": "mobile_get_screen_size"
        }
      }
    },
    {
      "kind": "mcp-tool-result",
      "actor": "mcp-server",
      "target": "mobile_get_screen_size",
      "evidence": {
        "response": {
          "id": 6,
          "jsonrpc": "2.0",
          "result": {
            "content": [
              {
                "text": "Device \"MCP_INPUT_CANARY_mobile_next__mobile_mcp\" not found. Use the mobile_list_available_devices tool to see available devices.. Please fix the issue and try again.",
                "type": "text"
              }
            ]
          }
        },
        "tool_name": "mobile_get_screen_size"
      }
    },
    {
      "kind": "mcp-tool-call",
      "actor": "mcp-client",
      "target": "tools/call",
      "evidence": {
        "id": 7,
        "jsonrpc": "2.0",
        "method": "tools/call",
        "params": {
          "arguments": {},
          "name": "mobile_list_available_devices"
        }
      }
    },
    {
      "kind": "mcp-tool-result",
      "actor": "mcp-server",
      "target": "mobile_list_available_devices",
      "evidence": {
        "response": {
          "id": 7,
          "jsonrpc": "2.0",
          "result": {
            "content": [
              {
                "text": "{\"devices\":[]}",
                "type": "text"
              }
            ]
          }
        },
        "tool_name": "mobile_list_available_devices"
      }
    },
    {
      "kind": "mcp-tool-call",
      "actor": "mcp-client",
      "target": "tools/call",
      "evidence": {
        "id": 8,
        "jsonrpc": "2.0",
        "method": "tools/call",
        "params": {
          "arguments": {
            "device": "MCP_INPUT_CANARY_mobile_next__mobile_mcp"
          },
          "name": "mobile_list_crashes"
        }
      }
    },
    {
      "kind": "mcp-tool-result",
      "actor": "mcp-server",
      "target": "mobile_list_crashes",
      "evidence": {
        "response": {
          "id": 8,
          "jsonrpc": "2.0",
          "result": {
            "content": [
              {
                "text": "Error: Command failed: /Users/zhuoran/Projects/MCP-SandboxScan/mcp-sandboxscan/corpus/clones/mobile-next__mobile-mcp/node_modules/mobilecli/bin/mobilecli-darwin-arm64 device crashes list --device MCP_INPUT_CANARY_mobile_next__mobile_mcp\nerror finding device: device not found: MCP_INPUT_CANARY_mobile_next__mobile_mcp\n",
                "type": "text"
              }
            ],
            "isError": true
          }
        },
        "tool_name": "mobile_list_crashes"
      }
    },
    {
      "kind": "mcp-tool-call",
      "actor": "mcp-client",
      "target": "tools/call",
      "evidence": {
        "id": 9,
        "jsonrpc": "2.0",
        "method": "tools/call",
        "params": {
          "arguments": {
            "device": "MCP_INPUT_CANARY_mobile_next__mobile_mcp"
          },
          "name": "mobile_list_elements_on_screen"
        }
      }
    },
    {
      "kind": "mcp-tool-result",
      "actor": "mcp-server",
      "target": "mobile_list_elements_on_screen",
      "evidence": {
        "response": {
          "id": 9,
          "jsonrpc": "2.0",
          "result": {
            "content": [
              {
                "text": "Device \"MCP_INPUT_CANARY_mobile_next__mobile_mcp\" not found. Use the mobile_list_available_devices tool to see available devices.. Please fix the issue and try again.",
                "type": "text"
              }
            ]
          }
        },
        "tool_name": "mobile_list_elements_on_screen"
      }
    },
    {
      "kind": "mcp-tool-call",
      "actor": "mcp-client",
      "target": "tools/call",
      "evidence": {
        "id": 10,
        "jsonrpc": "2.0",
        "method": "tools/call",
        "params": {
          "arguments": {
            "device": "MCP_INPUT_CANARY_mobile_next__mobile_mcp",
            "x": 1.0,
            "y": 1.0
          },
          "name": "mobile_long_press_on_screen_at_coordinates"
        }
      }
    },
    {
      "kind": "mcp-tool-result",
      "actor": "mcp-server",
      "target": "mobile_long_press_on_screen_at_coordinates",
      "evidence": {
        "response": {
          "id": 10,
          "jsonrpc": "2.0",
          "result": {
            "content": [
              {
                "text": "Device \"MCP_INPUT_CANARY_mobile_next__mobile_mcp\" not found. Use the mobile_list_available_devices tool to see available devices.. Please fix the issue and try again.",
                "type": "text"
              }
            ]
          }
        },
        "tool_name": "mobile_long_press_on_screen_at_coordinates"
      }
    },
    {
      "kind": "env-read",
      "actor": "scanner",
      "target": "MCP_SANDBOXSCAN_CANARY",
      "evidence": {
        "source_id": "EnvVar: MCP_SANDBOXSCAN_CANARY",
        "value_len": 38
      }
    },
    {
      "kind": "file-read",
      "actor": "scanner",
      "target": "/var/folders/kc/c74q_vx95dx4__wm8dtz6q540000gn/T/mcp-sandboxscan-canaries/mobile_next__mobile_mcp.txt",
      "evidence": {
        "content_len": 39,
        "source_id": "FileRead: /var/folders/kc/c74q_vx95dx4__wm8dtz6q540000gn/T/mcp-sandboxscan-canaries/mobile_next__mobile_mcp.txt"
      }
    },
    {
      "kind": "tool-input-observed",
      "actor": "scanner",
      "target": "mobile_get_crash:$.arguments.device",
      "evidence": {
        "content_len": 40,
        "path": "$.arguments.device",
        "source_id": "ToolInput: mobile_get_crash $.arguments.device",
        "tool": "mobile_get_crash"
      }
    },
    {
      "kind": "tool-input-observed",
      "actor": "scanner",
      "target": "mobile_get_crash:$.arguments.id",
      "evidence": {
        "content_len": 40,
        "path": "$.arguments.id",
        "source_id": "ToolInput: mobile_get_crash $.arguments.id",
        "tool": "mobile_get_crash"
      }
    },
    {
      "kind": "tool-input-observed",
      "actor": "scanner",
      "target": "mobile_click_on_screen_at_coordinates:$.arguments.device",
      "evidence": {
        "content_len": 40,
        "path": "$.arguments.device",
        "source_id": "ToolInput: mobile_click_on_screen_at_coordinates $.arguments.device",
        "tool": "mobile_click_on_screen_at_coordinates"
      }
    },
    {
      "kind": "tool-input-observed",
      "actor": "scanner",
      "target": "mobile_get_orientation:$.arguments.device",
      "evidence": {
        "content_len": 40,
        "path": "$.arguments.device",
        "source_id": "ToolInput: mobile_get_orientation $.arguments.device",
        "tool": "mobile_get_orientation"
      }
    },
    {
      "kind": "tool-input-observed",
      "actor": "scanner",
      "target": "mobile_get_screen_size:$.arguments.device",
      "evidence": {
        "content_len": 40,
        "path": "$.arguments.device",
        "source_id": "ToolInput: mobile_get_screen_size $.arguments.device",
        "tool": "mobile_get_screen_size"
      }
    },
    {
      "kind": "tool-input-observed",
      "actor": "scanner",
      "target": "mobile_list_crashes:$.arguments.device",
      "evidence": {
        "content_len": 40,
        "path": "$.arguments.device",
        "source_id": "ToolInput: mobile_list_crashes $.arguments.device",
        "tool": "mobile_list_crashes"
      }
    },
    {
      "kind": "tool-input-observed",
      "actor": "scanner",
      "target": "mobile_list_elements_on_screen:$.arguments.device",
      "evidence": {
        "content_len": 40,
        "path": "$.arguments.device",
        "source_id": "ToolInput: mobile_list_elements_on_screen $.arguments.device",
        "tool": "mobile_list_elements_on_screen"
      }
    },
    {
      "kind": "tool-input-observed",
      "actor": "scanner",
      "target": "mobile_long_press_on_screen_at_coordinates:$.arguments.device",
      "evidence": {
        "content_len": 40,
        "path": "$.arguments.device",
        "source_id": "ToolInput: mobile_long_press_on_screen_at_coordinates $.arguments.device",
        "tool": "mobile_long_press_on_screen_at_coordinates"
      }
    },
    {
      "kind": "sink-observed",
      "actor": "scanner",
      "target": "mcp-tool-result",
      "evidence": {
        "sink": {
          "path": "$.exploration_results[0].result.content[0].text",
          "type": "McpToolResultText",
          "value": "Error: Command failed: /Users/zhuoran/Projects/MCP-SandboxScan/mcp-sandboxscan/corpus/clones/mobile-next__mobile-mcp/node_modules/mobilecli/bin/mobilecli-darwin-arm64 device crashes get MCP_INPUT_CANARY_mobile_next__mobile_mcp --device MCP_INPUT_CANARY_mobile_next__mobile_mcp\nerror finding device: device not found: MCP_INPUT_CANARY_mobile_next__mobile_mcp\n"
        },
        "text_len": 358
      }
    },
    {
      "kind": "sink-observed",
      "actor": "scanner",
      "target": "mcp-tool-result",
      "evidence": {
        "sink": {
          "path": "$.exploration_results[1].result.content[0].text",
          "type": "McpToolResultText",
          "value": "Device \"MCP_INPUT_CANARY_mobile_next__mobile_mcp\" not found. Use the mobile_list_available_devices tool to see available devices.. Please fix the issue and try again."
        },
        "text_len": 166
      }
    },
    {
      "kind": "sink-observed",
      "actor": "scanner",
      "target": "mcp-tool-result",
      "evidence": {
        "sink": {
          "path": "$.exploration_results[2].result.content[0].text",
          "type": "McpToolResultText",
          "value": "Device \"MCP_INPUT_CANARY_mobile_next__mobile_mcp\" not found. Use the mobile_list_available_devices tool to see available devices.. Please fix the issue and try again."
        },
        "text_len": 166
      }
    },
    {
      "kind": "sink-observed",
      "actor": "scanner",
      "target": "mcp-tool-result",
      "evidence": {
        "sink": {
          "path": "$.exploration_results[3].result.content[0].text",
          "type": "McpToolResultText",
          "value": "Device \"MCP_INPUT_CANARY_mobile_next__mobile_mcp\" not found. Use the mobile_list_available_devices tool to see available devices.. Please fix the issue and try again."
        },
        "text_len": 166
      }
    },
    {
      "kind": "sink-observed",
      "actor": "scanner",
      "target": "mcp-tool-result",
      "evidence": {
        "sink": {
          "path": "$.exploration_results[4].result.content[0].text",
          "type": "McpToolResultText",
          "value": "{\"devices\":[]}"
        },
        "text_len": 14
      }
    },
    {
      "kind": "sink-observed",
      "actor": "scanner",
      "target": "mcp-tool-result",
      "evidence": {
        "sink": {
          "path": "$.exploration_results[5].result.content[0].text",
          "type": "McpToolResultText",
          "value": "Error: Command failed: /Users/zhuoran/Projects/MCP-SandboxScan/mcp-sandboxscan/corpus/clones/mobile-next__mobile-mcp/node_modules/mobilecli/bin/mobilecli-darwin-arm64 device crashes list --device MCP_INPUT_CANARY_mobile_next__mobile_mcp\nerror finding device: device not found: MCP_INPUT_CANARY_mobile_next__mobile_mcp\n"
        },
        "text_len": 318
      }
    },
    {
      "kind": "sink-observed",
      "actor": "scanner",
      "target": "mcp-tool-result",
      "evidence": {
        "sink": {
          "path": "$.exploration_results[6].result.content[0].text",
          "type": "McpToolResultText",
          "value": "Device \"MCP_INPUT_CANARY_mobile_next__mobile_mcp\" not found. Use the mobile_list_available_devices tool to see available devices.. Please fix the issue and try again."
        },
        "text_len": 166
      }
    },
    {
      "kind": "sink-observed",
      "actor": "scanner",
      "target": "mcp-tool-result",
      "evidence": {
        "sink": {
          "path": "$.exploration_results[7].result.content[0].text",
          "type": "McpToolResultText",
          "value": "Device \"MCP_INPUT_CANARY_mobile_next__mobile_mcp\" not found. Use the mobile_list_available_devices tool to see available devices.. Please fix the issue and try again."
        },
        "text_len": 166
      }
    },
    {
      "kind": "flow-detected",
      "actor": "scanner",
      "target": "McpToolResultText",
      "evidence": {
        "confidence": "high",
        "sink_type": "McpToolResultText",
        "snippet": "MCP_INPUT_CANARY_mobile_next__mobile_mcp",
        "source_id": "ToolInput: mobile_click_on_screen_at_coordinates $.arguments.device"
      }
    },
    {
      "kind": "flow-detected",
      "actor": "scanner",
      "target": "McpToolResultText",
      "evidence": {
        "confidence": "high",
        "sink_type": "McpToolResultText",
        "snippet": "MCP_INPUT_CANARY_mobile_next__mobile_mcp",
        "source_id": "ToolInput: mobile_get_crash $.arguments.device"
      }
    },
    {
      "kind": "flow-detected",
      "actor": "scanner",
      "target": "McpToolResultText",
      "evidence": {
        "confidence": "high",
        "sink_type": "McpToolResultText",
        "snippet": "MCP_INPUT_CANARY_mobile_next__mobile_mcp",
        "source_id": "ToolInput: mobile_get_crash $.arguments.id"
      }
    },
    {
      "kind": "flow-detected",
      "actor": "scanner",
      "target": "McpToolResultText",
      "evidence": {
        "confidence": "high",
        "sink_type": "McpToolResultText",
        "snippet": "MCP_INPUT_CANARY_mobile_next__mobile_mcp",
        "source_id": "ToolInput: mobile_get_orientation $.arguments.device"
      }
    },
    {
      "kind": "flow-detected",
      "actor": "scanner",
      "target": "McpToolResultText",
      "evidence": {
        "confidence": "high",
        "sink_type": "McpToolResultText",
        "snippet": "MCP_INPUT_CANARY_mobile_next__mobile_mcp",
        "source_id": "ToolInput: mobile_get_screen_size $.arguments.device"
      }
    },
    {
      "kind": "flow-detected",
      "actor": "scanner",
      "target": "McpToolResultText",
      "evidence": {
        "confidence": "high",
        "sink_type": "McpToolResultText",
        "snippet": "MCP_INPUT_CANARY_mobile_next__mobile_mcp",
        "source_id": "ToolInput: mobile_list_crashes $.arguments.device"
      }
    },
    {
      "kind": "flow-detected",
      "actor": "scanner",
      "target": "McpToolResultText",
      "evidence": {
        "confidence": "high",
        "sink_type": "McpToolResultText",
        "snippet": "MCP_INPUT_CANARY_mobile_next__mobile_mcp",
        "source_id": "ToolInput: mobile_list_elements_on_screen $.arguments.device"
      }
    },
    {
      "kind": "flow-detected",
      "actor": "scanner",
      "target": "McpToolResultText",
      "evidence": {
        "confidence": "high",
        "sink_type": "McpToolResultText",
        "snippet": "MCP_INPUT_CANARY_mobile_next__mobile_mcp",
        "source_id": "ToolInput: mobile_long_press_on_screen_at_coordinates $.arguments.device"
      }
    }
  ],
  "sources": [
    {
      "type": "EnvVar",
      "key": "MCP_SANDBOXSCAN_CANARY",
      "value": "MCP_ENV_CANARY_mobile_next__mobile_mcp"
    },
    {
      "type": "FileRead",
      "path": "/var/folders/kc/c74q_vx95dx4__wm8dtz6q540000gn/T/mcp-sandboxscan-canaries/mobile_next__mobile_mcp.txt",
      "content": "MCP_FILE_CANARY_mobile_next__mobile_mcp"
    },
    {
      "type": "ToolInput",
      "tool": "mobile_get_crash",
      "path": "$.arguments.device",
      "content": "MCP_INPUT_CANARY_mobile_next__mobile_mcp"
    },
    {
      "type": "ToolInput",
      "tool": "mobile_get_crash",
      "path": "$.arguments.id",
      "content": "MCP_INPUT_CANARY_mobile_next__mobile_mcp"
    },
    {
      "type": "ToolInput",
      "tool": "mobile_click_on_screen_at_coordinates",
      "path": "$.arguments.device",
      "content": "MCP_INPUT_CANARY_mobile_next__mobile_mcp"
    },
    {
      "type": "ToolInput",
      "tool": "mobile_get_orientation",
      "path": "$.arguments.device",
      "content": "MCP_INPUT_CANARY_mobile_next__mobile_mcp"
    },
    {
      "type": "ToolInput",
      "tool": "mobile_get_screen_size",
      "path": "$.arguments.device",
      "content": "MCP_INPUT_CANARY_mobile_next__mobile_mcp"
    },
    {
      "type": "ToolInput",
      "tool": "mobile_list_crashes",
      "path": "$.arguments.device",
      "content": "MCP_INPUT_CANARY_mobile_next__mobile_mcp"
    },
    {
      "type": "ToolInput",
      "tool": "mobile_list_elements_on_screen",
      "path": "$.arguments.device",
      "content": "MCP_INPUT_CANARY_mobile_next__mobile_mcp"
    },
    {
      "type": "ToolInput",
      "tool": "mobile_long_press_on_screen_at_coordinates",
      "path": "$.arguments.device",
      "content": "MCP_INPUT_CANARY_mobile_next__mobile_mcp"
    }
  ],
  "sinks": [
    {
      "type": "McpToolResultText",
      "path": "$.exploration_results[0].result.content[0].text",
      "value": "Error: Command failed: /Users/zhuoran/Projects/MCP-SandboxScan/mcp-sandboxscan/corpus/clones/mobile-next__mobile-mcp/node_modules/mobilecli/bin/mobilecli-darwin-arm64 device crashes get MCP_INPUT_CANARY_mobile_next__mobile_mcp --device MCP_INPUT_CANARY_mobile_next__mobile_mcp\nerror finding device: device not found: MCP_INPUT_CANARY_mobile_next__mobile_mcp\n"
    },
    {
      "type": "McpToolResultText",
      "path": "$.exploration_results[1].result.content[0].text",
      "value": "Device \"MCP_INPUT_CANARY_mobile_next__mobile_mcp\" not found. Use the mobile_list_available_devices tool to see available devices.. Please fix the issue and try again."
    },
    {
      "type": "McpToolResultText",
      "path": "$.exploration_results[2].result.content[0].text",
      "value": "Device \"MCP_INPUT_CANARY_mobile_next__mobile_mcp\" not found. Use the mobile_list_available_devices tool to see available devices.. Please fix the issue and try again."
    },
    {
      "type": "McpToolResultText",
      "path": "$.exploration_results[3].result.content[0].text",
      "value": "Device \"MCP_INPUT_CANARY_mobile_next__mobile_mcp\" not found. Use the mobile_list_available_devices tool to see available devices.. Please fix the issue and try again."
    },
    {
      "type": "McpToolResultText",
      "path": "$.exploration_results[4].result.content[0].text",
      "value": "{\"devices\":[]}"
    },
    {
      "type": "McpToolResultText",
      "path": "$.exploration_results[5].result.content[0].text",
      "value": "Error: Command failed: /Users/zhuoran/Projects/MCP-SandboxScan/mcp-sandboxscan/corpus/clones/mobile-next__mobile-mcp/node_modules/mobilecli/bin/mobilecli-darwin-arm64 device crashes list --device MCP_INPUT_CANARY_mobile_next__mobile_mcp\nerror finding device: device not found: MCP_INPUT_CANARY_mobile_next__mobile_mcp\n"
    },
    {
      "type": "McpToolResultText",
      "path": "$.exploration_results[6].result.content[0].text",
      "value": "Device \"MCP_INPUT_CANARY_mobile_next__mobile_mcp\" not found. Use the mobile_list_available_devices tool to see available devices.. Please fix the issue and try again."
    },
    {
      "type": "McpToolResultText",
      "path": "$.exploration_results[7].result.content[0].text",
      "value": "Device \"MCP_INPUT_CANARY_mobile_next__mobile_mcp\" not found. Use the mobile_list_available_devices tool to see available devices.. Please fix the issue and try again."
    }
  ],
  "flows": [
    {
      "source_id": "ToolInput: mobile_click_on_screen_at_coordinates $.arguments.device",
      "sink_type": "McpToolResultText",
      "snippet": "MCP_INPUT_CANARY_mobile_next__mobile_mcp",
      "confidence": "high"
    },
    {
      "source_id": "ToolInput: mobile_get_crash $.arguments.device",
      "sink_type": "McpToolResultText",
      "snippet": "MCP_INPUT_CANARY_mobile_next__mobile_mcp",
      "confidence": "high"
    },
    {
      "source_id": "ToolInput: mobile_get_crash $.arguments.id",
      "sink_type": "McpToolResultText",
      "snippet": "MCP_INPUT_CANARY_mobile_next__mobile_mcp",
      "confidence": "high"
    },
    {
      "source_id": "ToolInput: mobile_get_orientation $.arguments.device",
      "sink_type": "McpToolResultText",
      "snippet": "MCP_INPUT_CANARY_mobile_next__mobile_mcp",
      "confidence": "high"
    },
    {
      "source_id": "ToolInput: mobile_get_screen_size $.arguments.device",
      "sink_type": "McpToolResultText",
      "snippet": "MCP_INPUT_CANARY_mobile_next__mobile_mcp",
      "confidence": "high"
    },
    {
      "source_id": "ToolInput: mobile_list_crashes $.arguments.device",
      "sink_type": "McpToolResultText",
      "snippet": "MCP_INPUT_CANARY_mobile_next__mobile_mcp",
      "confidence": "high"
    },
    {
      "source_id": "ToolInput: mobile_list_elements_on_screen $.arguments.device",
      "sink_type": "McpToolResultText",
      "snippet": "MCP_INPUT_CANARY_mobile_next__mobile_mcp",
      "confidence": "high"
    },
    {
      "source_id": "ToolInput: mobile_long_press_on_screen_at_coordinates $.arguments.device",
      "sink_type": "McpToolResultText",
      "snippet": "MCP_INPUT_CANARY_mobile_next__mobile_mcp",
      "confidence": "high"
    }
  ],
  "summary": {
    "num_sources": 10,
    "num_sinks": 8,
    "num_flows": 8,
    "has_external_to_prompt_flow": true
  }
}